Workbook

Sheet test
A1: Question | B1: Answer | C1: A | D1: B | E1: C | G1: Explaniation if needed | H1: Category | I1: Sub Category | J1: File Name pulled from
A2: (Refer to figure 15 FAA-CT-8080-2H) At what time does the visibility improve to greater than 6 statute miles? | B2: B | C2: 051200Z | D2: 051600Z | E2: 051524Z | G2: At 051600Z, the TAF indicates "P6SM," meaning visibility improves to greater than 6 statute miles. | H2: Weather | I2: TAF | J2: TAF2 and KEY
A3: (Refer to figure 15 FAA-CT-8080-2H) What does "BECMG 0522/0524 20013G20KT" indicate? | B3: A | C3: A gradual change occurring between 0522Z and 0524Z. | D3: A temporary change lasting between 0522Z and 0524Z. | E3: A wind shift to 220° at 20 knots occurring at 0522Z. | G3: "BECMG" signifies a gradual change expected during the specified time period. | H3: Weather | I3: TAF | J3: TAF2 and KEY
A4: (Refer to figure 15 FAA-CT-8080-2H) What is the forecasted ceiling at 051200Z? | B4: B | C4: Overcast at 3,000 feet. | D4: Broken at 3,000 feet. | E4: Overcast at 2,000 feet. | G4: "BKN030" indicates a broken layer at 3,000 feet, which is the ceiling. | H4: Weather | I4: TAF | J4: TAF2 and KEY
A5: (Refer to figure 15 FAA-CT-8080-2H) During the period 0600Z to 0606Z, what is the probability of thunderstorms? | B5: C | C5: 60% | D5: 30% | E5: 40% | G5: "PROB40" indicates a 40% probability of thunderstorms and rain. | H5: Weather | I5: TAF | J5: TAF2 and KEY
A6: (Refer to figure 15 FAA-CT-8080-2H) What weather phenomenon is associated with "OVC008CB"? | B6: B | C6: Cumulonimbus clouds with fog. | D6: Cumulonimbus clouds with thunderstorms. | E6: Stratocumulus clouds with light rain. | G6: "CB" signifies cumulonimbus clouds, typically associated with thunderstorms. | H6: Weather | I6: TAF | J6: TAF2 and KEY
A7: (Refer to figure 15 FAA-CT-8080-2H) What visibility is expected during the "TEMPO 0513/0516" period? | B7: A | C7: 1 1/2 statute miles | D7: 5 statute miles | E7: Greater than 6 statute miles | G7: During this temporary period, visibility is reduced to 1 1/2SM due to mist, "BR." | H7: Weather | I7: TAF | J7: TAF2 and KEY
A8: (Refer to figure 15) What is the wind forecast for 0608Z? | B8: C | C8: 140° at 8 knots | D8: 200° at 13 knots, gusting to 20 knots | E8: 210° at 15 knots | G8: At 0608Z, the TAF indicates "21015KT," meaning wind from 210° at 15 knots. | H8: Weather | I8: TAF | J8: TAF2 and KEY
A9: (Refer to figure 15 FAA-CT-8080-2H) What does "P6SM SCT040" mean in the forecast starting at 0608Z? | B9: B | C9: Visibility less than 6 statute miles with scattered clouds at 4,000 feet. | D9: Visibility greater than 6 statute miles with scattered clouds at 4,000 feet. | E9: No significant weather with overcast skies at 4,000 feet. | G9: "P6SM" means visibility is greater than 6 statute miles, and "SCT040" indicates scattered clouds at 4,000 feet. | H9: Weather | I9: TAF | J9: TAF2 and KEY
A10: (Refer to Figure 15 FAA-CT-8080-2H) What is the forecast visibility for KMEM at the beginning of the TAF period (1218Z)? | B10: C | C10: 1 mile | D10: 3 statute miles | E10: 5 statute miles | H10: Weather | I10: TAF | J10: TAF Quiz- key
A11: (Refer to Figure 15 FAA-CT-8080-2H) According to the TAF, what type of weather is expected from 1220Z to 1222Z? | B11: A | C11: Thunderstorms with rain and overcast conditions | D11: Snow showers with overcast conditions | E11: Light rain with scattered clouds | H11: Weather | I11: TAF | J11: TAF Quiz- key
A12: (Refer to Figure 15 FAA-CT-8080-2H) What is the expected wind direction and speed at KMEM from 1222Z onward? | B12: C | C12: 020° at 8 knots | D12: 350° at 12 knots | E12: 330° at 15 knots with gusts to 20 knots | H12: Weather | I12: TAF | J12: TAF Quiz- key
A13: (Refer to Figure 15 FAA-CT-8080-2H) What is the forecast ceiling for KMEM from 1220Z to 1222Z? | B13: A | C13: 800 feet AGL | D13: 1,500 feet AGL | E13: 3,000 feet AGL | H13: Weather | I13: TAF | J13: TAF Quiz- key
A14: (Refer to Figure 15 FAA-CT-8080-2H) When is fog expected to occur according to the TAF? | B14: B | C14: From 1312Z to 1314Z | D14: From 1212Z to 1214Z | E14: From 1306Z to 1308Z | H14: Weather | I14: TAF | J14: TAF Quiz- key
A15: (Refer to Figure 15 FAA-CT-8080-2H) What is the forecast wind direction and speed at KMEM from 1202Z to 1205Z? | B15: A | C15: 350° at 12 knots | D15: 020° at 8 knots | E15: 330° at 15 knots, gusting to 20 knots | H15: Weather | I15: TAF | J15: TAF Quiz- key
A16: (Refer to Figure 15 FAA-CT-8080-2H) The forecast ceiling at KMEM from 1200Z to 1220Z is: | B16: B | C16: Clear skies | D16: Overcast at 800 feet AGL | E16: Broken clouds at 3,000 feet AGL | H16: Weather | I16: TAF | J16: TAF Quiz- key
A17: What factor would tend to increase the density altitude? | B17: B | C17: An increase in barometric pressure | D17: An increase in ambient temperature | E17: A decrease in relative humidity | H17: Weather | J17: Weather MC Test - Key 2
A18: With a low-level temperature inversion with high relative humidity, what weather conditions would you expect? | B18: A | C18: Smooth air, poor visibility, fog, haze, or low clouds | D18: Turbulent air, poor visibility, fog, low stratus type clouds, and showery precipitation | E18: Light wind shear, poor visibility, haze, and light rain | H18: Weather | J18: =J17 -> Weather MC Test - Key 2
A19: What is a temperature inversion? | B19: A | C19: Cold air trapped near the surface under warmer air | D19: Warm air trapped near the surface under cooler air | E19: A rapid drop in temperature with altitude | H19: Weather | J19: =J18 -> Weather MC Test - Key 2
A20: What is the effect of humidity on air density? | B20: B | C20: Increased humidity increases air density. | D20: Increased humidity decreases air density. | E20: Humidity has no effect on air density. | H20: Weather | J20: ='end of unit questions'!J33 -> Weather MC Test - Key 2
A21: What is the primary difference between stable and unstable air? | B21: C | C21: Stable air is always dry, while unstable air is always moist. | D21: Stable air has vertical movement, while unstable air does not. | E21: Stable air is associated with clear weather, while unstable air is associated with thunderstorms. | H21: Weather | J21: =J20 -> Weather MC Test - Key 2
A22: What is the primary characteristic of unstable air? | B22: A | C22: It has vertical movement. | D22: It is always dry. | E22: It is always cold. | H22: Weather | J22: =J21 -> Weather MC Test - Key 2
A23: What is the primary factor that determines the stability of an air mass? | B23: C | C23: The amount of wind. | D23: The altitude of the air mass. | E23: The temperature and moisture content of the air. | H23: Weather | J23: =J22 -> Weather MC Test - Key 2
A24: What are the characteristics of stable air? | B24: B | C24: Poor visibility and intermittent precipitation | D24: Poor visibility and steady precipitation | E24: Good visibility and steady precipitation | H24: Weather | J24: =J23 -> Weather MC Test - Key 2
A25: Which weather reports provide real-time observations? | B25: A | C25: METAR | D25: TAF | E25: SIGMET | H25: Weather | I25: Metar | J25: =J24 -> Weather MC Test - Key 2
A26: How does high humidity affect drone performance? | B26: A | C26: Reduce lift | D26: Increase lift | E26: No effect | H26: Weather | J26: =J25 -> Weather MC Test - Key 2
A27: What type of front often brings thunderstorms and gusty winds? | B27: C | C27: Stationary front | D27: Warm front | E27: Cold Front | H27: Weather | J27: =J26 -> Weather MC Test - Key 2
A28: What situation is most conducive to the formation of radiation fog? | B28: A | C28: Warm, moist air over low, flatland areas on clear calm nights | D28: Moist tropical air moving over cold, offshore water | E28: The movement of cold air over much warmer water | H28: Weather | J28: =J27 -> Weather MC Test - Key 2
A29: The two types of clouds that unmanned aircraft operators should be concerned about are: | B29: C | C29: Standing lenticular and stratocumulus | D29: Nimbostratus and cumulonimbus | E29: Cumulonimbus and standing lenticular | H29: Weather | J29: ='end of unit questions'!J32 -> Weather MC Test - Key 2
A30: Every physical process of weather is accompanied by or is a result of a _____________ | B30: C | C30: Movement of air | D30: Pressure differential | E30: Heat Exchange | H30: Weather | J30: =J29 -> Weather MC Test - Key 2
A31: What is the standard temperature at sea level? | B31: A | C31: 15°C or 59°F | D31: 29.92°C | E31: 1013.2°F | H31: Weather | J31: =J30 -> Weather MC Test - Key 2
A32: The development of thermals depends upon _____________ | B32: B | C32: A counter clockwise circulation of air | D32: Solar Heating | E32: Temperature Inversions | H32: Weather | J32: =J31 -> Weather MC Test - Key 2
A33: Wind Shear can exist at…. | B33: A | C33: All Altitudes | D33: Low Altitudes | E33: High Altitudes | H33: Weather | J33: =J32 -> Weather MC Test - Key 2
A34: A stable air mass is most likely to have which characteristic | B34: C | C34: Showery precipitation | D34: Turbulent Air | E34: Poor surface visibility | H34: Weather | J34: ='end of unit questions'!J31 -> Weather MC Test - Key 2
A35: What would decrease the stability of an air mass? | B35: B | C35: Cooling from below | D35: Warming from below | E35: Decrease in water Vapor | H35: Weather | J35: =J34 -> Weather MC Test - Key 2
A36: The cloud ceiling is at 800ft. What is the highest you can operate your drone? | B36: C | C36: 200 FT AGL | D36: 800 FT AGL | E36: 300 Ft AGL | H36: Weather | J36: =J35 -> Weather MC Test - Key 2
A37: What conditions are necessary for the formation of thunderstorms? | B37: B | C37: High humidity, high Temperatures and cumulus clouds | D37: High humidity, lifting force and unstable conditions | E37: Lifting force, moist air and extensive cloud cover | H37: Weather | J37: =J36 -> Weather MC Test - Key 2
A38: What is the effect of a high-density altitude on aircraft performance? | B38: C | C38: It increases aircraft performance. | D38: It has no effect on aircraft performance. | E38: It decreases aircraft performance. | H38: Weather | J38: =J37 -> Weather MC Test - Key 2
A39: Thunderstorms which generally produce the most intense hazards to aircraft are | B39: B | C39: Steady-state thunderstorms | D39: Squall line thunderstorms | E39: Warm front thunderstorms | H39: Weather | J39: ='end of unit questions'!J30 -> Weather MC Test - Key 2
A40: One in flight condition necessary for structural icing to form is… | B40: B | C40: Stratiform clouds | D40: Visible moisture | E40: Small temperature & dewpoint spread | H40: Weather | J40: =J39 -> Weather MC Test - Key 2
A41: What environment is most conductive to front formulation? | B41: B | C41: Surface temperature is below freezing, air temperature is below freezing | D41: Dewpoint of surface is below freezing, dewpoint is above freezing | E41: Surface temperature is above freezing, air temperature is below freezing | H41: Weather | J41: =J40 -> Weather MC Test - Key 2
A42: What effect does high density altitude have on the efficiency of a UA propeller? Select one: | B42: A | C42: Propeller efficiency is decreased | D42: Propeller efficiency is increased | E42: Density altitude does not affect propeller efficiency | H42: Weather | J42: ='end of unit questions'!J29 -> Weather MC Test - Key 2
A43: What are characteristics of a moist, unstable air mass? Select one: | B43: A | C43: Turbulence and showery precipitation | D43: Haze and smoke | E43: Poor visibility and smooth air | H43: Weather | J43: =J42 -> Weather MC Test - Key 2
A44: What are the characteristics of stable air? | B44: B | C44: Poor visibility and intermittent precipitation | D44: Poor visibility and steady precipitation | E44: Good visibility and steady precipitation | H44: Weather | J44: =J43 -> Weather MC Test - Key 2
A45: How does high humidity affect drone performance? | B45: B | C45: True | D45: False | H45: Weather | J45: =J44 -> Weather MC Test - Key 2
A46: What is the relationship between air density and aircraft performance? | B46: B | C46: As air density decreases, aircraft performance increases. | D46: As air density decreases, aircraft performance decreases. | E46: Air density has no impact on aircraft performance. | H46: Weather | J46: =J45 -> Weather MC Test - Key 2
A47: As humidity increases, air density decreases. | B47: A | C47: True | D47: False | H47: Weather | J47: =J46 -> Weather MC Test - Key 2
A48: The two types of clouds that unmanned aircraft operators should be concerned about are: | B48: C | C48: Standing lenticular and stratocumulus | D48: Nimbostratus and cumulonimbus | E48: Cumulonimbus and standing lenticular | H48: Weather | J48: =J47 -> Weather MC Test - Key 2
A49: Structural icing can occur | B49: C | C49: Only when it is snowing | D49: Only when it is below 0 °F | E49: When flying though moisture and the temperature where the moisture is striking the aircraft is 32 °F or colder | H49: Weather | J49: =J48 -> Weather MC Test - Key 2
A50: A METAR is a surface weather observation report. | B50: A | C50: True | D50: False | H50: Weather | I50: Metar | J50: ='end of unit questions'!J28 -> Weather MC Test - Key 2
A51: A METAR is usually updated | B51: B | C51: Whenever the observer can get to it | D51: On a regular time interval | E51: Whenever the weather changes | H51: Weather | I51: Metar | J51: =J50 -> Weather MC Test - Key 2
A52: A TAF is updated | B52: B | C52: Once per day | D52: Four times per day | E52: Eight times per day | H52: Weather | I52: TAF | J52: ='end of unit questions'!J26 -> Weather MC Test - Key 2
A53: A TAF is for a _____ hour period Select one: | B53: C | C53: 12 | D53: 24 | E53: 24 or 30 | H53: Weather | I53: TAF | J53: =J52 -> Weather MC Test - Key 2
A54: A TEMPO is: | B54: C | C54: Only valid for 30 minutes | D54: A temporary TAF | E54: A forecast change group | H54: Weather | J54: =J53 -> Weather MC Test - Key 2
A55: What is the standard sea level pressure in millibars? | B55: B | C55: 29.92 mb | D55: 1013.2 mb | E55: 34 mb | H55: Weather | J55: Weather MC Test - Key
A56: When flying near natural or man-made obstructions, an unmanned aircraft operator can expect: | B56: C | C56: Turbulence | D56: Changes in wind direction & wind speed | E56: All the above | H56: Weather | J56: Weather MC Test - Key
A57: The leeward side of a mountain or obstacle is: | B57: A | C57: The downwind side | D57: The side the wind contacts first | E57: The side you are standing on | H57: Weather | J57: Weather MC Test - Key
A58: Refer to FAA-CT-8080-2H, Figure 12.) Which stations are reporting weather that would prohibit UAS operations? | B58: B | C58: KINK and KMDW | D58: KMDW and KJFK | E58: KINK and KBOI | H58: Weather | I58: Metar | J58: Remaining Weather questions for James
A59: (Refer to FAA-CT-8080-2H, Figure 12.) What are the current conditions for Chicago Midway Airport (KMDW)? | B59: A | C59: Sky 700 feet overcast, visibility 1-1/2SM, rain. | D59: Sky 7,000 feet overcast, visibility 1-1/2SM, heavy rain. | E59: Sky 700 feet overcast, visibility 11, occasionally 2SM, with rain. | H59: Weather | I59: Metar | J59: Remaining Weather questions for James
A60: A TAF report has winds at 16010KT. What does this mean? | B60: C | C60: Wind is from 160° true 10 kilometers per hour | D60: Wind is from 160° magnetic at 10 knots | E60: Wind is from 160° true at 10 knots | G60: TAF or MetAR is a land-based report so the tower or station is stationary and the observations are taken from the ground not moving like aircraft so you use a true heading which is the north pole. | H60: Weather | I60: TAF | J60: Remaining Weather questions for James
A61: Which types of clouds are specifically identified by name in a TAF forecast? | B61: C | C61: Altostratus and cirrus | D61: Stratus and stratocumulus | E61: Cumulonimbus and towering cumulus | H61: Weather | J61: Remaining Weather questions for James
A62: Refer to FAA-CT-8080-2H, Figure 75 area 6. During preflight planning you plan to operate in R-205, where would you find additional info regarding this airspace? | B62: A | C62: In the aeronautical information manual | D62: In the Charts Supplements US | E62: In the special Use Airspace of the chart. | H62: Airports & Airspace | J62: Additional Airspace Maps - Key
A63: (Refer to Figure 26, area 4) You have been hired to inspect the tower under construction at 46.90N and 98.55W, near Jamestown Regional (JMS). What must you receive prior to your flying an UA in this area? | B63: A | C63: Authorization from the National Park Service | D63: Authorization from the military | E63: Authorization from the ATC | H63: Airports & Airspace | J63: Additional Airspace Maps - Key
A64: (Refer to Figure 22, Area 1) The floor of the controlled airspace overlying the Sandpoint Airport is: | B64: A | C64: 700 feet MSL | D64: 700 feet AGL | E64: At the surface | H64: Airports & Airspace | I64: Classes | J64: Additional Airspace Maps - Key
A65: (Refer to Figure 25, Area 5) What is the elevation range of the Class B airspace? | B65: A | C65: Surface to 11,000 feet AGL | D65: Surface to 1,100 feet MSL | E65: Surface to 11,000 feet MSL | H65: Airports & Airspace | I65: Classes | J65: Additional Airspace Maps - Key
A66: (Refer to Figure 22, South of Area 1) You have been hired to inspect the railroad near Cocolalla. Do you need ATC approval? | B66: A | C66: Yes, it is in Class E Airspace from the surface | D66: No, it is Class G Airspace | E66: No, it is in Class E Airspace from 700 feet | H66: Airports & Airspace | I66: Classes | J66: Additional Airspace Maps - Key
A67: Refer to figure 24, Northeast of area 1) What is the ceiling of Class D Airspace surrounding Majors (GVT) airport? | B67: A | C67: 3,000 feet MSL | D67: 3,000 feet AGL | E67: 1,200 feet AGL | H67: Airports & Airspace | I67: Classes | J67: Additional Airspace Maps - Key
A68: (Refer to Figure 20, Area 1) The Fentress NALF Airport (NFE) is in what type of airspace? | B68: A | C68: Class C | D68: Class E | E68: Class G | H68: Airports & Airspace | I68: Classes | J68: Additional Airspace Maps - Key
A69: (Refer to Figure 21, Area 1) After receiving authorization from ATC to operate a small UA near Minot International airport (MOT) while the control tower is operational, which radio communication could be used to monitor manned aircraft and ATC communications? | B69: A | C69: UNICOM 122.95 | D69: ASOS 118.725 | E69: CT-118.2 | H69: Airports & Airspace | J69: Additional Airspace Maps - Key
A70: (Refer to Figure 21) What airport is located approximately 47 (degrees) 40 (minutes) N latitude and 101 (degrees) 26 (minutes) W longitude? | B70: A | C70: Mercer County | D70: Shemshenko | E70: Garrison | H70: Airports & Airspace | I70: L & L | J70: Additional Airspace Maps - Key
A71: (Refer to Figure 26, Area 2) While monitoring the Cooperstown CTAF you hear an aircraft announce that they are midfield left downwind to RWY 13. Where would the aircraft be relative to the runway? | B71: A | C71: East Side | D71: South Side | E71: West Side | H71: Airports & Airspace | I71: Runways | J71: Additional Airspace Maps - Key
A72: (Refer to Figure 25, Area 3) The floor of Class B airspace at Dallas Executive (RBD) is | B72: A | C72: At the surface | D72: 3,000 feet MSL | E72: 3,100 feet MSL | H72: Airports & Airspace | I72: Classes | J72: Additional Airspace Maps - Key
A73: (Refer to figure 78) You have been hired to use your sUAS to inspected the railroad tracks from Blencoe (SE of Sioux City) to Onawa. Will ATC authorization be required? | B73: A | C73: Yes, Onawa is in Class D airspace that is designated for an airport | D73: No, your entire flight is Class G airspace | E73: Yes, you must contact the Onawa control tower to operate within 5 miles of the airport | H73: Airports & Airspace | I73: Classes | J73: Additional Airspace Maps - Key
A74: (Refer to Figure 78) You have contracted to inspect towers located approximately 4NM South West of the Sioux Gateway (SUX) airport operating an UA. What is the maximum altitude above ground level (AGL) that you are authorized to operate over the top of the towers? | B74: A | C74: 400 feet AGL | D74: 402 feet AGL | E74: 802 feet AGL | H74: Airports & Airspace | J74: Additional Airspace Maps - Key
A75: Lines of latitude | B75: B | C75: Run perpendicular to the equator | D75: Run parallel to the equator | E75: Run diagonal to the equator | H75: Airports & Airspace | I75: L & L | J75: Airports & Airspace Test - key
A76: Lines of longitude run from the North Pole to the South Pole. | B76: A | C76: True | D76: False | H76: Airports & Airspace | I76: L & L | J76: Airports & Airspace Test - key
A77: The Prime Meridian runs through | B77: C | C77: Washington, DC | D77: Paris, France | E77: Greenwich, England | H77: Airports & Airspace | I77: L & L | J77: Airports & Airspace Test - key
A78: Which of the following is not a source of airport data? | B78: C | C78: Chart Supplement U.S. | D78: Aeronautical charts | E78: Airport newsletter | J78: Airports & Airspace Test - key
A79: The most comprehensive source of airport information is | B79: A | C79: Chart Supplement U.S. | D79: Aeronautical charts | E79: Notices to Airmen (NOTAMs) | J79: Airports & Airspace Test - key
A80: How often are sectional charts covering the continental U.S. updated? | B80: C | C80: Monthly | D80: Quarterly | E80: Semi-annually | J80: Airports & Airspace Test - key
A81: What is the scale on the terminal area chart? | B81: B | C81: 1:100,000 | D81: 1:250,000 | E81: 1:500,000 | J81: Airports & Airspace Test - key
A82: An sUAS operator can find out if they are operating near an airport and basic information about that airport by using a sectional chart. | B82: A | C82: True | D82: False | J82: Airports & Airspace Test - key
A83: An sUAS operator will not be able to determine what type of airspace they are operating in by using a sectional chart. | B83: B | C83: True | D83: False | J83: Airports & Airspace Test - key
A84: Which of the following is NOT a consideration of airspace classification? | B84: B | C84: Complexity of aircraft movements | D84: Number of passengers that use the closest airport | E84: Level of safety required | J84: Airports & Airspace Test - key
A85: An sUAS operator does not need prior authorization to fly in which airspace? | B85: C | C85: Class B | D85: Class E | E85: Class G | H85: Airports & Airspace | I85: Classes | J85: Airports & Airspace Test - key
A86: An sUAS can fly in a prohibited area because there is no one inside it. | B86: B | C86: True | D86: False - | J86: Airports & Airspace Test - key
A87: Before flying in a military operations area, an sUAS operator should do what to find out if it is active? | B87: B | C87: Call your local military base | D87: Refer to the sectional chart legend | E87: Call the nearest FAA office | J87: Airports & Airspace Test - key
A88: When a temporary flight restriction is issued over a disaster area, it is still ok to fly your sUAS if you are trying to help. | B88: B | C88: True | D88: False | J88: Airports & Airspace Test - key
A89: Which airport type is the largest group in the United States? | B89: C | C89: Commercial service airports | D89: Reliever airports | E89: General aviation airports | J89: Airports & Airspace Test - key
A90: A hobbyist sUAS operator does not need to notify a non-towered, general aviation, private airport that they are flying nearby within 5 miles. | B90: B | C90: True | D90: False | J90: Airports & Airspace Test - key
A91: When near a non-towered airport, an sUAS operator should monitor what frequency? | B91: C | C91: CT | D91: ATIS | E91: CTAF | J91: Airports & Airspace Test - key
A92: Runway numbers are based on the | B92: B | C92: Airport design standards | D92: Approach direction | E92: Runway length | J92: Airports & Airspace Test - key
A93: The standard airport traffic pattern is to the _________ unless otherwise noted. | B93: A | C93: Left | D93: Right | J93: Airports & Airspace Test - key
A94: Refer to FAA-CT-8080-2H, Figure 75 area 6. During preflight planning you plan to operate in R-2305, where would you find additional info regarding this airspace? | B94: B | C94: In the special Use Airspace of the chart. | J94: Airports & Airspace Test - key
A95: You have been hired to inspect a railroad near Cocolalla. (Refer to figure 22 south of area 1) Do you need approval from ATC? | B95: B | C95: Yes, it is class E airspace from the surface | D95: No it is Class G airspace | E95: No it is Class E from the surface | H95: Airports & Airspace | I95: Classes | J95: Airports & Airspace Test - key
A96: (Refer to FAA-CT-8080-2H, Figure 20 Area 1) The Fentress NALF Airport (NFE) is in what type of airspace? | B96: B | C96: Class C | D96: Class E | E96: Class G | H96: Airports & Airspace | I96: Classes | J96: Airports & Airspace Test - key
A97: (Refer to FAA-CT-800-2H, Figure 21). What is the airport located approximately 47 degrees 40 minutes N latitude and 101 degrees 26 minutes w longitude? | B97: C | C97: Mercer County | D97: Shemshenko | E97: Garrison | H97: Airports & Airspace | I97: L &L | J97: Airports & Airspace Test - key
A98: While monitoring CTAF you hear an aircraft announce they where midfield left downwind to RWY 13. Where is the aircraft relative to the runway? | B98: A | C98: East | D98: South | E98: West | H98: Airports & Airspace | I98: Runways | J98: Airports & Airspace Test - key
A99: While monitoring the Barnes CTAF you hear an aircraft announce that they are midfield left downwind to RWY 11. Where would the aircraft be relative to the runway? | B99: C | C99: The aircraft is North | D99: The aircraft is West | E99: The Aircraft is East | H99: Airports & Airspace | I99: Runways | J99: airspace Patterns Ws key chat
A100: While monitoring the Coventon CTAF you hear an aircraft announce that they are midfield left downwind to RWY 27. Where would the aircraft be relative to the runway? | B100: A | C100: The aircraft is South | D100: The aircraft is West | E100: The Aircraft is North | H100: Airports & Airspace | I100: Runways | J100: airspace Patterns Ws key chat
...

Sheet end of unit questions
A1: Question | B1: Answer | C1: Choice A | D1: Choice B | E1: Choice C | F1: Choice D | G1: Explaniation if needed | H1: Category | I1: Sub Category | J1: File Name
A2: What are the two types of clouds that pose hazards to unmanned aircraft operators? | B2: A | C2: Cumulonimbus and lenticular altocumulus | D2: Stratus and cirrus | E2: Cumulus and nimbus | F2: Altostratus and cumulus | H2: Weather | J2: Weather Part 2 MC - Key
A3: What is the main reason why frost is a flight safety hazard for unmanned aircraft? | B3: A | C3: Frost can cause the aircraft to lose lift and increase drag. | D3: Frost can damage the aircraft's engine. | E3: Frost can make the aircraft more difficult to control. | F3: Frost can make the aircraft more visible to other aircraft. | H3: Weather | J3: Weather Part 2 MC - Key
A4: What is the relationship between temperature and dew point? | B4: B | C4: Temperature is the amount of heat in the air, while dew point is the amount of moisture in the air. | D4: Temperature is the measure of how hot or cold the air is, while dew point is the temperature at which the air becomes saturated with moisture. | E4: Temperature is the measure of how fast the air is moving, while dew point is the measure of how much moisture is in the air. | F4: Temperature and dew point are not related. | H4: Weather | J4: Weather Part 2 MC - Key
A5: What is a temperature inversion and how does it affect weather and pollutants? | B5: B | C5: A temperature inversion is when the temperature decreases with altitude, leading to clear skies and good visibility. | D5: A temperature inversion is when the temperature increases with altitude, trapping weather and pollutants below. | E5: A temperature inversion is when the temperature remains constant with altitude, causing unpredictable weather patterns. | F5: A temperature inversion is a sudden drop in temperature at a specific altitude, leading to strong winds and turbulence. | H5: Weather | J5: Weather Part 2 MC - Key
A6: What is the main difference between a surface-based temperature inversion and a frontal inversion? | B6: C | C6: A surface-based inversion occurs during the day, while a frontal inversion occurs at night. | D6: A surface-based inversion is caused by warm air spreading over cold air, while a frontal inversion is caused by cold air spreading over warm air. | E6: A surface-based inversion is caused by the cooling of the ground at night, while a frontal inversion is caused by the interaction of different air masses. | F6: There is no significant difference between the two types of inversions. | H6: Weather | J6: Weather Part 2 MC - Key
A7: How does icing affect an unmanned aircraft's ability to fly? | B7: C | C7: Icing increases the aircraft's lift and reduces drag, making it easier to fly. | D7: Icing has no impact on an unmanned aircraft's ability to fly. | E7: Icing adds weight, reduces lift, and increases drag, making it harder to fly. | F7: Icing only affects the aircraft's appearance and does not affect its performance. | H7: Weather | J7: Weather Part 2 MC - Key
A8: What are the characteristics of standing lenticular altocumulus clouds and why should unmanned aircraft operators avoid them? | B8: C | C8: These clouds are small and fluffy, indicating calm air conditions. | D8: These clouds are large and dark, indicating strong winds and turbulence. | E8: These clouds are smooth and lens-shaped, indicating strong turbulence and should be avoided. | F8: These clouds are low-lying and often produce rain, making them hazardous to fly through. | H8: Weather | J8: Weather Part 2 MC - Key
A9: What is the recommended action for an unmanned aircraft operator if they encounter a frontal zone? | B9: C | C9: Continue flying as usual, as frontal zones are not a significant hazard. | D9: Increase altitude to avoid the frontal zone. | E9: Suspend operations until the front has passed through the area. | F9: Fly through the frontal zone quickly to minimize exposure. | H9: Weather | J9: Weather Part 2 MC - Key
A10: What is the main difference between a cumulonimbus cloud and a lenticular altocumulus cloud? | B10: A | C10: Cumulonimbus clouds are associated with thunderstorms, while lenticular altocumulus clouds are associated with mountain waves. | D10: Cumulonimbus clouds are small and fluffy, while lenticular altocumulus clouds are large and dark. | E10: Cumulonimbus clouds are formed by warm air rising, while lenticular altocumulus clouds are formed by cold air sinking. | F10: There is no significant difference between the two types of clouds. | H10: Weather | J10: Weather Part 2 MC - Key
A11: What is the recommended action for an unmanned aircraft operator if they see stratified clouds during a preflight visual assessment? | B11: B | C11: Suspend operations immediately, as stratified clouds indicate unstable air. | D11: Continue flying as usual, as stratified clouds indicate stable air. | E11: Increase altitude to avoid the stratified clouds. | F11: Fly through the stratified clouds quickly to minimize exposure. | H11: Weather | J11: Weather Part 2 MC - Key
A12: What is the minimum visibility requirement for unmanned flight operations from the ground control station? | B12: C | C12: 1 statute mile | D12: 2 statute miles | E12: 3 statute miles | F12: 5 statute miles | H12: Weather | J12: Weather Part 2 MC - Key
A13: What is the main reason why a drone operator should be aware of the wind direction and speed before flying in a mountainous area? | B13: C | C13: Wind can affect the aircraft's visibility. | D13: Wind can affect the aircraft's altitude. | E13: Wind can affect the aircraft's speed and direction. | F13: Wind can affect the aircraft's battery life. | H13: Weather | J13: Weather Part 2 MC - Key
... A19: What is the main reason why a drone operator should be aware of the dew point before flying? | B19: C | C19: To determine the best time of day to fly. | D19: To avoid flying in areas with high winds. | E19: To avoid flying in areas with fog or frost, which can be dangerous for unmanned aircraft. | F19: To determine the best altitude to fly. | H19: Weather | J19: Weather Part 2 MC - Key
A20: While operating around buildings, the Remote Pilot in Command should be aware of the creation of wind gusts that | B20: C | C20: enhance stability and imagery. | D20: increase performance of the aircraft. | E20: change rapidly in direction and speed causing turbulence. | H20: Weather | J20: Remaining Weather questions for James
A21: What should be obtained by the RPIC in order to receive a complete weather overview for the planned flight. | B21: B | C21: An outlook briefing | D21: A standard briefing | E21: Abbreviated briefing | H21: Weather | J21: Remaining Weather questions for James
A22: The predictions you considered during your preflight weather evaluation indicate that an unstable air mass is approaching your area. Which of those not be a problem for your upcoming operation? | B22: A | C22: Stratiform clouds | D22: Thunderstorms | E22: Turbulent conditions | H22: Weather | J22: Remaining Weather questions for James
A23: Which combination of atmospheric conditions will reduce aircraft takeoff and climb performance? | B23: C | C23: Low temperature, low relative humidity, and low density altitude. | D23: High temperature, low relative humidity, and low density altitude. | E23: High temperature, high relative humidity, and high density altitude. | H23: Weather | J23: Remaining Weather questions for James
A24: What is the primary reason why wind can cause turbulence around obstacles? | B24: A | C24: The wind is forced to change direction and speed around obstacles. | D24: The wind is blocked by obstacles, creating a vacuum. | E24: The wind is slowed down by obstacles, creating a pocket of calm air. | H24: Weather | J24: Weather MC Test - Key
A25: What is the standard temperature decrease per 1,000 feet above sea level? | B25: B | C25: 1°C | D25: 2°C | E25: 3.5°C | H25: Weather | J25: Weather MC Test - Key
A26: A TAF is for a 10-mile radius around the issuing airport. | B26: B | C26: True | D26: False | H26: Weather | J26: ='end of unit questions'!J27 -> Weather MC Test - Key 2
A27: A METAR does not contain information related to which of the following: | B27: C | C27: Altimeter | D27: Visibility | E27: Turbulence | H27: Weather | J27: =test!J51 -> Weather MC Test - Key 2
A28: A surface weather observation is a weather forecast. | B28: B | C28: True | D28: False | H28: Weather | J28: =test!J49 -> Weather MC Test - Key 2
A29: What is the primary reason why wind shear is considered a dangerous hazard to aircraft? | B29: C | C29: It can cause the aircraft to lose altitude rapidly. | D29: It can cause the aircraft to fly too fast. | E29: It can cause the aircraft to lose control. | H29: Weather | J29: =test!J41 -> Weather MC Test - Key 2
A30: What is the primary cause of low-level wind shear? | B30: C | C30: Changes in altitude. | D30: Changes in air pressure. | E30: Sudden changes in wind speed and direction. | H30: Weather | J30: =test!J38 -> Weather MC Test - Key 2
A31: One weather phenomenon which will always occur when flying across a front is | B31: C | C31: Stability of the air mass | D31: Type of precipitation | E31: Wind Direction | H31: Weather | J31: =test!J33 -> Weather MC Test - Key 2
A32: In which situation is fog likely to form? | B32: B | C32: A warm, moist air mass on the windward side of the mountains | D32: An air mass, moving in land from the coast in winter | E32: A light breeze blowing colder air out to the sea. | H32: Weather | J32: =test!J28 -> Weather MC Test - Key 2
A33: What is the primary reason why air density decreases as altitude increases? | B33: B | C33: The air gets colder at higher altitudes. | D33: There are fewer air molecules at higher altitudes. | E33: The air pressure increases at higher altitudes. | H33: Weather | J33: =test!J19 -> Weather MC Test - Key 2
A34: (Refer to figure 15 FAA-CT-8080-2H) At what time does the visibility improve to greater than 6 statute miles? | B34: B | C34: 051200Z | D34: 051600Z | E34: 051524Z | G34: At 051600Z, the TAF indicates "P6SM," meaning visibility improves to greater than 6 statute miles. | H34: Weather | I34: TAF | J34: TAF2 and KEY
A35: (Refer to figure 15 FAA-CT-8080-2H) What does "BECMG 0522/0524 20013G20KT" indicate? | B35: A | C35: A gradual change occurring between 0522Z and 0524Z. | D35: A temporary change lasting between 0522Z and 0524Z. | E35: A wind shift to 220° at 20 knots occurring at 0522Z. | G35: "BECMG" signifies a gradual change expected during the specified time period. | H35: Weather | I35: TAF | J35: TAF2 and KEY
A36: (Refer to figure 15 FAA-CT-8080-2H) What is the forecasted ceiling at 051200Z? | B36: B | C36: Overcast at 3,000 feet. | D36: Broken at 3,000 feet. | E36: Overcast at 2,000 feet. | G36: "BKN030" indicates a broken layer at 3,000 feet, which is the ceiling. | H36: Weather | I36: TAF | J36: TAF2 and KEY
A37: (Refer to figure 15 FAA-CT-8080-2H) During the period 0600Z to 0606Z, what is the probability of thunderstorms? | B37: C | C37: 60% | D37: 30% | E37: 40% | G37: "PROB40" indicates a 40% probability of thunderstorms and rain. | H37: Weather | I37: TAF | J37: TAF2 and KEY
A38: (Refer to figure 15 FAA-CT-8080-2H) What weather phenomenon is associated with "OVC008CB"? | B38: B | C38: Cumulonimbus clouds with fog. | D38: Cumulonimbus clouds with thunderstorms. | E38: Stratocumulus clouds with light rain. | G38: "CB" signifies cumulonimbus clouds, typically associated with thunderstorms. | H38: Weather | I38: TAF | J38: TAF2 and KEY
A39: (Refer to figure 15 FAA-CT-8080-2H) What visibility is expected during the "TEMPO 0513/0516" period? | B39: A | C39: 1 1/2 statute miles | D39: 5 statute miles | E39: Greater than 6 statute miles | G39: During this temporary period, visibility is reduced to 1 1/2SM due to mist, "BR." | H39: Weather | I39: TAF | J39: TAF2 and KEY
A40: (Refer to figure 15) What is the wind forecast for 0608Z? | B40: C | C40: 140° at 8 knots | D40: 200° at 13 knots, gusting to 20 knots | E40: 210° at 15 knots | G40: At 0608Z, the TAF indicates "21015KT," meaning wind from 210° at 15 knots. | H40: Weather | I40: TAF | J40: TAF2 and KEY
A41: (Refer to figure 15 FAA-CT-8080-2H) What does "P6SM SCT040" mean in the forecast starting at 0608Z? | B41: B | C41: Visibility less than 6 statute miles with scattered clouds at 4,000 feet. | D41: Visibility greater than 6 statute miles with scattered clouds at 4,000 feet. | E41: No significant weather with overcast skies at 4,000 feet. | G41: "P6SM" means visibility is greater than 6 statute miles, and "SCT040" indicates scattered clouds at 4,000 feet. | H41: Weather | I41: TAF | J41: TAF2 and KEY
A42: (Refer to Figure 15 FAA-CT-8080-2H) What is the forecast visibility for KMEM at the beginning of the TAF period (1218Z)? | B42: C | C42: 1 mile | D42: 3 statute miles | E42: 5 statute miles | H42: Weather | I42: TAF | J42: TAF Quiz- key
A43: (Refer to Figure 15 FAA-CT-8080-2H) According to the TAF, what type of weather is expected from 1220Z to 1222Z? | B43: A | C43: Thunderstorms with rain and overcast conditions | D43: Snow showers with overcast conditions | E43: Light rain with scattered clouds | H43: Weather | I43: TAF | J43: TAF Quiz- key
A44: (Refer to Figure 15 FAA-CT-8080-2H) What is the expected wind direction and speed at KMEM from 1222Z onward? | B44: C | C44: 020° at 8 knots | D44: 350° at 12 knots | E44: 330° at 15 knots with gusts to 20 knots | H44: Weather | I44: TAF | J44: TAF Quiz- key
A45: (Refer to Figure 15 FAA-CT-8080-2H) What is the forecast ceiling for KMEM from 1220Z to 1222Z? | B45: A | C45: 800 feet AGL | D45: 1,500 feet AGL | E45: 3,000 feet AGL | H45: Weather | I45: TAF | J45: TAF Quiz- key
A46: (Refer to Figure 15 FAA-CT-8080-2H) When is fog expected to occur according to the TAF? | B46: B | C46: From 1312Z to 1314Z | D46: From 1212Z to 1214Z | E46: From 1306Z to 1308Z | H46: Weather | I46: TAF | J46: TAF Quiz- key
A47: (Refer to Figure 15 FAA-CT-8080-2H) What is the forecast wind direction and speed at KMEM from 1202Z to 1205Z? | B47: A | C47: 350° at 12 knots | D47: 020° at 8 knots | E47: 330° at 15 knots, gusting to 20 knots | H47: Weather | I47: TAF | J47: TAF Quiz- key
A48: (Refer to Figure 15 FAA-CT-8080-2H) The forecast ceiling at KMEM from 1200Z to 1220Z is: | B48: B | C48: Clear skies | D48: Overcast at 800 feet AGL | E48: Broken clouds at 3,000 feet AGL | H48: Weather | I48: TAF | J48: TAF Quiz- key
A50: What is the primary purpose of aeronautical charts? | B50: B | C50: To display airline schedules | D50: To plan and conduct flight operations | E50: To show weather forecasts | H50: Airports & airspace | J50: Airports and Airspace questions slides 32-62 -key
A51: Which chart type covers the entire U.S. and is revised semi-annually? | B51: B | C51: Terminal Area Chart | D51: Sectional Chart | E51: IFR Enroute Chart | H51: Airports & airspace | I51: Sectional & Terminal Charts | J51: Airports and Airspace questions slides 32-62 -key
A52: What is the scale of a sectional chart? | B52: B | C52: 1:250,000 | D52: 1:500,000 | E52: 1:1,000,000 | H52: Airports & airspace | I52: Sectional & Terminal Charts | J52: Airports and Airspace questions slides 32-62 -key
A53: Terminal Area Charts are designed to show more detail around which type of airports? | B53: C | C53: Private airports | D53: Military airports | E53: Busiest airports | H53: Airports & airspace | I53: Sectional & Terminal Charts | J53: Airports and Airspace questions slides 32-62 -key
A54: What is the scale of a Terminal Area Chart? | B54: A | C54: 1:250,000 | D54: 1:500,000 | E54: 1:750,000 | H54: Airports & airspace | I54: Sectional & Terminal Charts | J54: Airports and Airspace questions slides 32-62 -key
A55: What should sUAS operators use to interpret chart symbols during planning? | B55: B | C55: FAA drone app | D55: Chart User’s Guide | E55: Airport directory | H55: Airports & airspace | J55: Airports and Airspace questions slides 32-62 -key
A56: Which tab in the Chart User’s Guide includes airspace and airport information? | B56: A | C56: VFR Sectional & TAC | D56: IFR Planning | E56: Obstacle Clearance | H56: Airports & airspace | J56: Airports and Airspace questions slides 32-62 -key
A57: What is the benefit of being familiar with chart symbols before the Part 107 test? | B57: B | C57: You can skip questions | D57: The test will be easier | E57: You won’t need the legend | H57: Airports & airspace | J57: Airports and Airspace questions slides 32-62 -key
A58: What symbol on a sectional chart represents a VFR checkpoint? | B58: B | C58: A parachute icon | D58: A small flag | E58: A dashed circle | H58: Airports & airspace | J58: Airports and Airspace questions slides 32-62 -key
A59: What is the purpose of the CTAF frequency listed on a chart? | B59: B | C59: To contact ATC for clearance | D59: To monitor traffic at non-towered airports | E59: To report weather conditions | H59: Airports & airspace | J59: Airports and Airspace questions slides 32-62 -key
A60: Why is runway elevation important for sUAS operators? | B60: B | C60: It determines the drone’s battery life | D60: It affects the risk of collision with aircraft | E60: It helps calculate wind speed | H60: Airports & airspace | J60: Airports and Airspace questions slides 32-62 -key
A61: What does the magenta color of an airport symbol indicate? | B61: B | C61: Military airport | D61: No control tower | E61: Temporary closure | H61: Airports & airspace | J61: Airports and Airspace questions slides 32-62 -key
A62: What does the blue color of an airport symbol indicate? | B62: A | C62: Controlled airport | D62: Private airport | E62: No control tower | H62: Airports & airspace | J62: Airports and Airspace questions slides 32-62 -key
A63: What does a communication box on a sectional chart provide? | B63: B | C63: Obstacle height | D63: Radio frequencies | E63: Runway length | H63: Airports & airspace | J63: Airports and Airspace questions slides 32-62 -key
A64: What does the number in parentheses below an obstacle height indicate? | B64: B | C64: Height above sea level | D64: Height above ground level | E64: Clearance altitude | H64: Airports & airspace | J64: Airports and Airspace questions slides 32-62 -key
A65: What is the typical size of a quadrant used for MEF calculations? | B65: B | C65: 10’ x 10’ | D65: 30’ x 30’ | E65: 60’ x 60’ | H65: Airports & airspace | J65: Airports and Airspace questions slides 32-62 -key
A66: What does an MEF value of 35 indicate? | B66: A | C66: 3,500 feet MSL | D66: 350 feet AGL | E66: 3,500 feet AGL | H66: Airports & airspace | J66: Airports and Airspace questions slides 32-62 -key
A68: What is the primary purpose of the National Airspace System (NAS)? | B68: B | C68: To increase airline profits | D68: To protect people and property | E68: To reduce fuel consumption | J68: Airports & airspace Slides 1-30 - key- chat
A69: What are the two main purposes of the Air Traffic Control (ATC) system? | B69: B | C69: Reduce fuel costs and increase speed | D69: Prevent collisions and organize traffic | E69: Promote tourism and reduce delays | J69: Airports & airspace Slides 1-30 - key- chat
A70: What makes integrating sUAS into the NAS complex? | B70: C | C70: Lack of funding | D70: Too few users | E70: Many moving pieces and risks | J70: Airports & airspace Slides 1-30 - key- chat
A71: Which method is universally used in aviation to locate points on Earth? | B71: C | C71: Street addresses | D71: GPS only | E71: Latitude and Longitude | J71: Airports & airspace Slides 1-30 - key- chat
A72: Lines of latitude run | B72: B | C72: From North Pole to South Pole | D72: Parallel to the equator | E72: From East to West | J72: Airports & airspace Slides 1-30 - key- chat
A73: Lines of longitude start at | B73: C | C73: Equator | D73: North Pole | E73: Prime Meridian | J73: Airports & airspace Slides 1-30 - key- chat
A74: The continental U.S. lies between which degrees of latitude? | B74: B | C74: 10° and 30° | D74: 25° and 49° | E74: 50° and 70° | J74: Airports & airspace Slides 1-30 - key- chat
A75: How many minutes are in each degree of latitude or longitude? | B75: A | C75: 60 | D75: 30 | E75: 90 | J75: Airports & airspace Slides 1-30 - key- chat
A76: Which of the following is NOT an airport ownership classification? | B76: C | C76: Civil or Private | D76: Military/government | E76: Commercial | J76: Airports & airspace Slides 1-30 - key- chat
A77: Towered airports have | B77: B | C77: No control tower | D77: A control tower with controllers | E77: No radio communication | J77: Airports & airspace Slides 1-30 - key- chat
A78: What should sUAS operators be aware of when operating within 5 miles of an airport? | B78: B | C78: Weather only | D78: Ownership, aircraft type, and control specifics | E78: Runway length | J78: Airports & airspace Slides 1-30 - key- chat
A79: Which source contains the most comprehensive airport information? | B79: C | C79: NOTAMs | D79: Aeronautical Charts | E79: Chart Supplement U.S. | J79: Airports & airspace Slides 1-30 - key- chat
... A84: How often is ATIS information updated? | B84: C | C84: Daily | D84: Weekly | E84: Hourly or as needed | J84: Airports & airspace Slides 1-30 - key- chat
A85: What are the two types of aeronautical charts relevant to sUAS operators? | B85: B | C85: Road and terrain charts | D85: Sectional and terminal area charts | E85: Weather and traffic charts | I85: Sectional & Terminal Charts | J85: Airports & airspace Slides 1-30 - key- chat
A86: Convert 46.75° to degrees and minutes. | B86: A | C86: 46° 45' | D86: 46° 75' | E86: 47° | I86: L &L | J86: Airports & airspace Slides 1-30 - key- chat
A87: Convert 98.2° to degrees and minutes. | B87: A | C87: 98° 12' | D87: 98° 20' | E87: 98° 22' | I87: L &L | J87: Airports & airspace Slides 1-30 - key- chat
A90: Part 107 primarily governs which type of sUAS operations? | B90: B | C90: Recreational flights only | D90: Nonrecreational and commercial sUAS operations | E90: Military drone operations | H90: Regulations | I90: Slide 3 – Applicability
A91: Which operation originally required a waiver under early Part 107 rules? | B91: B | C91: Daytime flight in Class G airspace | D91: Night operations and flight over people | E91: Operations under 400 feet AGL | H91: Regulations | I91: Slide 4 – Applicability
A92: What credential is required to fly under Part 107 without special exemptions? | B92: B | C92: Airworthiness certificate | D92: Remote Pilot Certificate | E92: Private pilot license | H92: Regulations | I92: Slide 5 – Applicability
A93: Which operation is NOT subject to Part 107? | B93: B | C93: Civil sUAS flights for compensation | D93: Recreational flights conducted under 49 USC 44809 | E93: Commercial photography flights | H93: Regulations | I93: Slide 6 – Applicability Exclusions
A94: Which role has final authority and responsibility for a Part 107 operation? | B94: C | C94: Visual Observer | D94: Person manipulating the controls | E94: Remote Pilot in Command | H94: Regulations | I94: Slide 9 – 10 Roles
A95: Under Part 107, who is ultimately responsible for the safety of the flight? | B95: C | C95: The VO | D95: The aircraft manufacturer | E95: The RPIC | H95: Regulations | I95: Slide 10 – RPIC
A96: Which action is required before each flight under Part 107? | B96: B | C96: Submitting a flight plan to ATC | D96: Conducting a preflight inspection | E96: Obtaining a waiver | H96: Regulations | I96: Slide 12 – RPIC Duties
A97: The person manipulating the flight controls must be: | B97: B | C97: The RPIC at all times | D97: Under direct supervision if not certified | E97: A certificated flight instructor | H97: Regulations | I97: Slide 14–15 Person Manipulating Controls
A98: Which statement about Visual Observers is correct? | B98: C | C98: VOs are mandatory for all flights | D98: VOs must hold a Remote Pilot Certificate | E98: VOs are optional but recommended depending on mission complexity | H98: Regulations | I98: Slide 16 – Visual Observer
A99: Which factor must the RPIC assess before flight? | B99: B | C99: Pilot salary | D99: Weather, airspace, and crew readiness | E99: FAA processing time | H99: Regulations | I99: Slide 19 – Flight Crew Management
A100: If a sUAS goes out of VLOS for more than 15 seconds, the RPIC should: | B100: B | C100: Continue the mission | D100: Initiate a failsafe return-to-home | E100: Contact ATC | H100: Regulations | I100: Slide 21 – Communication
A101: Nonrecreational drones must be registered under which regulation? | B101: C | C101: Part 91 | D101: Part 107 only | E101: Part 47 or Part 48 | H101: Regulations | I101: Slide 25 – Aircraft Registration
... A124: Night operations without a waiver require: | B124: B | C124: ATC coordination | D124: Updated training and anticollision lighting | E124: A VO | H124: Regulations | I124: Slide 132 – Night Operations
A125: Where must a small unmanned aircraft’s serial number be listed when using either standard remote identification or a broadcast module? | B125: C | C125: The aircraft’s Document of Compliance. | D125: The manufacturer’s Method of Compliance. | E125: The Certificate of Aircraft Registration. | H125: Additional Topics | J125: My new questions May9
A126: During a flight of your small UA, you observe a hot air balloon entering the area. You should | B126: A | C126: Yield the right-of-way to the hot air balloon. | D126: Ensure the UA passes below, above, or ahead of the balloon. | E126: Expect the hot air balloon to climb above your altitude. | H126: Additional Topics | J126: My new questions May9
A127: When may a remote pilot reduce the intensity of an aircraft’s lights during a night flight? | B127: C | C127: At no time may the lights of an sUAS be reduced in intensity at night. | D127: When a manned aircraft is in the vicinity of the sUAS. | E127: When it is in the interest of safety to dim the aircraft’s lights. | H127: Additional Topics | J127: My new questions May9
A128: The refusal of a remote PIC to submit to a blood alcohol test when requested by a law enforcement officer | B128: A | C128: Is grounds for suspension or revocation of the remote pilot certificate. | D128: Can be delayed for up to 8 hours after the request. | E128: Has no consequences to the remote pilot certificate. | H128: Additional Topics | J128: My new questions May9
A129: (Refer to FAA-CT-8080-2H, Figure 24, Area 3, and Legend 1.) For information about the parachute operations at Tri-County Airport, refer to | B129: B | C129: Notes on the border of the chart. | D129: Chart Supplements U.S. | E129: The Notices to Airmen (NOTAM) publication. | H129: Additional Topics | J129: My new questions May9
A130: To avoid a possible collision with a manned airplane, you estimate that your small UA climbed to an altitude greater than 600 feet AGL. To whom must you report the deviation? | B130: C | C130: Air Traffic Control. | D130: The National Transportation Safety Board. | E130: Upon request of the Federal Aviation Administration. | H130: Additional Topics | J130: My new questions May9
A131: You have been hired as a remote pilot by a local TV news station to film breaking news with a small UA. You expressed a safety concern and the station manager has instructed you to 'fly first, ask questions later.' What type of hazardous attitude does this attitude represent? | B131: C | C131: Machismo. | D131: Invulnerability. | E131: Impulsivity. | H131: Additional Topics | J131: My new questions May9
A132: What does the IMSAFE checklist help an RPIC to assess before a flight? | B132: B | C132: The weather conditions at the flight location. | D132: The pilot's physical and mental readiness for the job. | E132: The aircraft's maintenance and safety records. | H132: Additional Topics | J132: My new questions May9
A133: What is the purpose of Crew Resource Management (CRM) in aeronautical decision-making? | B133: B | C133: To ensure that all team members have the necessary technical skills. | D133: To develop training for flight crews that focuses on using all available resources effectively. | E133: To minimize the costs associated with flight operations. | H133: Additional Topics | J133: My new questions May9
A134: What is the first step in dealing with hazardous attitudes? | B134: B | C134: Ignoring the attitude and hoping it goes away. | D134: Recognizing when you're having a hazardous thought. | E134: Acting on the attitude without thinking. | H134: Additional Topics | J134: My new questions May9
A135: What is the purpose of the 'six-sigma' process mentioned in relation to risk management? | B135: A | C135: To provide a framework for continuously improving risk assessment and decision-making in drone missions. | D135: To ensure that all team members have the necessary technical skills. | E135: To minimize the costs associated with flight operations. | H135: Additional Topics | J135: My new questions May9
...
